{
    "inputText": {
      "label": "Ranking",
      "isHeading": true,
      "headingIcon": "PiRankingBold",
      "type": "heading",
      "designType": "head"
    },
    "design": {
    "label1": "General Properties",
    "type": "design",
    "designType": "head"
  },
    "fieldLabel": {
      "label": "Field-Label",
      "defaultValue": "Ranking",
      "column": "column",
      "paragraph": "Type your question. Use @ to recall answer from previous question.",
      "designType": "general",
      "type": "input"
    },
    "options": {
      "label": "Options",
      "column": "column",
      "designType":"general",
      "field": "ranking",
      "type": "draggable-options",
      "option": [
        {
          "id": 1,
          "defaultLabel": "Item 1"
        },
        {
          "id": 2,
          "defaultLabel": "Item 2"
        },
        {
          "id": 3,
          "defaultLabel": "Item 3"
        }
      ]
    }
  }
  